pythons/__init__.py
pythons/assets/font/OFL.txt
pythons/assets/font/museo_moderno.ttf
pythons/assets/font/museo_moderno_medium.ttf
pythons/game.py
pythons-0.1.1.dist-info/entry_points.txt
pythons-0.1.1.dist-info/LICENSE
pythons-0.1.1.dist-info/WHEEL
pythons-0.1.1.dist-info/METADATA
pythons-0.1.1.dist-info/RECORD
