Metadata-Version: 2.1
Name: pythons
Version: 0.1.1
Summary: Yet another snake game written in Python
Home-page: https://github.com/julianolf/pythons
License: MIT
Keywords: snake,game,pygame
Author: Juliano Fernandes
Author-email: julianofernandes@gmail.com
Requires-Python: >=3.7,<4.0
Classifier: License :: OSI Approved :: MIT License
Classifier: Programming Language :: Python :: 3
Classifier: Programming Language :: Python :: 3.7
Classifier: Programming Language :: Python :: 3.8
Classifier: Topic :: Games/Entertainment
Classifier: Topic :: Software Development :: Libraries :: pygame
Requires-Dist: pygame (==2.0.0.dev10)
Project-URL: Repository, https://github.com/julianolf/pythons
